armagarch/ARMA.py
armagarch/VAR.py
armagarch/__init__.py
armagarch/dcc.py
armagarch/distModel.py
armagarch/empModel.py
armagarch/errors.py
armagarch/garch.py
armagarch/gjr.py
armagarch/meanModel.py
armagarch/multModel.py
armagarch/multiModel.py
armagarch/noconstant.py
armagarch/normalDist.py
armagarch/regARMA.py
armagarch/skewt.py
armagarch/tStudent.py
armagarch/tests.py
armagarch/volModel.py
armagarch/legacy/__init__.py
armagarch/legacy/basicFun.py
armagarch/legacy/legacygarch.py
armagarch-1.0.4.dist-info/LICENSE
armagarch-1.0.4.dist-info/METADATA
armagarch-1.0.4.dist-info/WHEEL
armagarch-1.0.4.dist-info/top_level.txt
armagarch-1.0.4.dist-info/RECORD
