Metadata-Version: 2.1
Name: armagarch
Version: 1.0.4
Summary: Library for flexible mean and volatility modelling
Home-page: https://github.com/iankhr/armagarch
Author: Ian Khrashchevskyi
Author-email: iankhr@yahoo.com
Classifier: Programming Language :: Python :: 3
Classifier: License :: OSI Approved :: MIT License
Classifier: Operating System :: OS Independent
Requires-Python: >=3.6
License-File: LICENSE
